chem_calc/4f.p
chem_calc/5d.p
chem_calc/R_cov_element.p
chem_calc/R_vdw_element.p
chem_calc/__init__.py
chem_calc/add4f5d.p
chem_calc/allelectrons.p
chem_calc/atomicnumber.p
chem_calc/atomicweight.p
chem_calc/atten_co.p
chem_calc/atten_inco.p
chem_calc/chem_calc.py
chem_calc/co_scatt.p
chem_calc/density.p
chem_calc/el_neg_chi.p
chem_calc/ex_energy.p
chem_calc/inco_scatt.p
chem_calc/ionenergy.p
chem_calc/pe_abs.p
chem_calc/period.p
chem_calc/sub4f5dabs.p
chem_calc/val_e.p
chem_calc/zaratio.p
chem_calc-0.0.3.dist-info/LICENSE
chem_calc-0.0.3.dist-info/METADATA
chem_calc-0.0.3.dist-info/WHEEL
chem_calc-0.0.3.dist-info/top_level.txt
chem_calc-0.0.3.dist-info/RECORD
