Metadata-Version: 2.1
Name: chem-calc
Version: 0.0.3
Summary: A package to calculate various stoichometric features of compounds.
Home-page: https://github.com/garne041/chem_calc
Author: Joy Garnett
Author-email: garne041@gmail.com
License: UNKNOWN
Platform: UNKNOWN
Classifier: Programming Language :: Python :: 3
Classifier: License :: OSI Approved :: MIT License
Classifier: Operating System :: OS Independent
Requires-Python: >=3.2
Requires-Dist: numpy
Requires-Dist: pandas
